ip_assembler-0.0.1.dist-info/DESCRIPTION.rst
ip_assembler-0.0.1.dist-info/WHEEL
ip_assembler-0.0.1.dist-info/RECORD
ip_assembler-0.0.1.dist-info/top_level.txt
ip_assembler-0.0.1.dist-info/metadata.json
ip_assembler-0.0.1.dist-info/METADATA
ip_assembler/models.py
ip_assembler/app_settings.py
ip_assembler/__init__.py
ip_assembler/views.py
ip_assembler/admin.py
ip_assembler/tasks.py
ip_assembler/forms.py
ip_assembler/migrations/0001_initial.py
ip_assembler/migrations/__init__.py
ip_assembler/management/commands/ip_assembler_test.py
ip_assembler/management/commands/__init__.py
