Metadata-Version: 2.0
Name: ip-assembler
Version: 0.0.1
Summary: Banned IP processing for .htaccess locations like Wordpress.
Home-page: https://github.com/dArignac/ip_assembler
Author: Alexander Herrmann
Author-email: darignac@gmail.com
License: MIT
Platform: UNKNOWN
Classifier: Development Status :: 4 - Beta
Classifier: Framework :: Django
Classifier: Intended Audience :: Developers
Classifier: License :: OSI Approved :: MIT License
Classifier: Natural Language :: English
Classifier: Operating System :: POSIX :: Linux
Classifier: Programming Language :: Python :: 3.4
Classifier: Topic :: Utilities
Requires-Dist: Django (>=1.6,<1.8)
Requires-Dist: django-shared
